logz/__init__.py
logz/logger_cls.py
logz/utils.py
pylogz-0.0.4.dist-info/LICENSE
pylogz-0.0.4.dist-info/METADATA
pylogz-0.0.4.dist-info/WHEEL
pylogz-0.0.4.dist-info/top_level.txt
pylogz-0.0.4.dist-info/RECORD
